mirage/__init__.py
mirage/data/sample0.png
mirage/data/sample1.tiff
mirage/data/sample2_image.tiff
mirage/data/sample2_reference.tiff
mirage/exceptions.py
mirage/pl/__init__.py
mirage/pl/plot_before_after.py
mirage/pl/plot_ssim.py
mirage/pl/utils.py
mirage/tests/test_model.py
mirage/tests/utils.py
mirage/tl/MIRAGE.py
mirage/tl/__init__.py
mirage/tl/get_data.py
mirage/tl/mesh.py
cellmirage-0.1.2.dist-info/METADATA
cellmirage-0.1.2.dist-info/WHEEL
cellmirage-0.1.2.dist-info/RECORD
