Metadata-Version: 2.1
Name: cellmirage
Version: 0.1.2
Summary: Efficient and scalable image registration (alignment) for multiplexed imaging data
License: MIT
Author: Doron Haviv
Author-email: havivd@mskcc.org
Maintainer: Tobias Krause
Maintainer-email: tobiaspk1@gmail.com
Requires-Python: >=3.9,<3.12
Classifier: License :: OSI Approved :: MIT License
Classifier: Programming Language :: Python :: 3
Classifier: Programming Language :: Python :: 3.9
Classifier: Programming Language :: Python :: 3.10
Classifier: Programming Language :: Python :: 3.11
Requires-Dist: matplotlib (>=3.6,<4.0)
Requires-Dist: numpy (>=1.26.3,<2.0.0)
Requires-Dist: opencv-python (>=4.9.0.80,<5.0.0.0)
Requires-Dist: scikit-image (>=0.22.0,<0.23.0)
Requires-Dist: tensorflow (>=2.8.4,<3.0.0)
Requires-Dist: tqdm (>=4.66.1,<5.0.0)
Requires-Dist: urllib3 (==1.26.6)
